{
  "key": "hipchat-markdown",
  "name": "Hipchat markdown",
  "description": "Hipchat markdown",
  "vendor": {
    "name": "Daniel Hreben",
    "url": "https://www.hipchat.com"
  },
  "links": {
    "self": "{{localBaseUrl}}/atlassian-connect.json",
    "homepage": "{{localBaseUrl}}"
  },
  "capabilities": {
    "hipchatApiConsumer": {
      "scopes": [
        "send_notification",
        "view_room"
      ],
      "avatar": {
        "url": "{{localBaseUrl}}/img/markdown_of.png",
        "url@2x": "{{localBaseUrl}}/img/markdown_of.png"
      }
    },
    "installable": {
      "callbackUrl": "{{localBaseUrl}}/installable"
    },
    "webhook": {
      "url": "{{localBaseUrl}}/webhook",
      "pattern": "^(/md|/markdown|/code md)",
      "event": "room_message",
      "name": "Render markdown",
      "authentication": "jwt"
    },
    "dialog": [
      {
        "key": "editor.dialog",
        "title": {
          "value": "Markdown editor"
        },
        "url": "{{localBaseUrl}}/dialog",
        "options": {
          "style": "normal",
          "primaryAction": {
            "name": {
              "value": "Send"
            },
            "key": "editor.dialog.action",
            "enabled": true
          },
          "size": {
            "width": "800px",
            "height": "600px"
          }
        }
      }
    ],
    "action": [
      {
        "key": "editor.open",
        "name": {
          "value": "Markdown editor"
        },
        "target": "editor.dialog",
        "location": "hipchat.input.action"
      }
    ]
  }
}
